tradingsystemsdata/__init__.py
tradingsystemsdata/dollar_exits.py
tradingsystemsdata/graph_data.py
tradingsystemsdata/indicator_entries.py
tradingsystemsdata/indicator_exits.py
tradingsystemsdata/ma_entries.py
tradingsystemsdata/marketdata.py
tradingsystemsdata/pnl.py
tradingsystemsdata/positions.py
tradingsystemsdata/reports.py
tradingsystemsdata/signals.py
tradingsystemsdata/systems.py
tradingsystemsdata/systems_params.py
tradingsystemsdata/targets.py
tradingsystemsdata/trades.py
tradingsystemsdata/utils.py
tradingsystemsdata/winloss.py
tradingsystemsdata-1.1.4.dist-info/LICENSE
tradingsystemsdata-1.1.4.dist-info/METADATA
tradingsystemsdata-1.1.4.dist-info/WHEEL
tradingsystemsdata-1.1.4.dist-info/top_level.txt
tradingsystemsdata-1.1.4.dist-info/RECORD
